nbctl/__init__.py
nbctl/constants.py
nbctl/logger.py
nbctl/shell.py
python3_nbctl-1.0.0.dist-info/AUTHORS
python3_nbctl-1.0.0.dist-info/LICENSE
python3_nbctl-1.0.0.dist-info/METADATA
python3_nbctl-1.0.0.dist-info/WHEEL
python3_nbctl-1.0.0.dist-info/entry_points.txt
python3_nbctl-1.0.0.dist-info/pbr.json
python3_nbctl-1.0.0.dist-info/top_level.txt
python3_nbctl-1.0.0.dist-info/RECORD
