Metadata-Version: 2.1
Name: python3-nbctl
Version: 1.0.0
Summary: convert jupyter *.ipynb file to markdown files
Home-page: https://www.xiexianbin.cn/
Author: xiexianbin
Author-email: me@xiexianbin.cn
Project-URL: Bug Tracker, https://github.com/x-actions/python3-nbctl/issues
Project-URL: Source Code, https://github.com/x-actions/python3-nbctl
Classifier: License :: OSI Approved :: Apache Software License
Classifier: Operating System :: POSIX :: Linux
Classifier: Programming Language :: Python :: 3
Classifier: Programming Language :: Python :: 3.6
Classifier: Programming Language :: Python :: 3.7
Classifier: Programming Language :: Python :: 3.8
Requires-Python: >=3.6
License-File: LICENSE
License-File: AUTHORS
Requires-Dist: pbr (>=5.5.0)
Requires-Dist: setuptools (==65.1.1)
Requires-Dist: nbconvert (==7.6.0)
Requires-Dist: nbformat (==5.9.0)
